examples/__init__.py
examples/steem/__init__.py
examples/steem/data_explorer.py
examples/steem/helpers.py
examples/steem/sync_bloackchain.py
examples/steem/yodu_example.py
yodu/__init__.py
yodu/settings.py
yodu/algo_spec/__init__.py
yodu/algo_spec/helper.py
yodu/api/__init__.py
yodu/api/main.py
yodu/db/__init__.py
yodu/db/es/__init__.py
yodu/db/es/es_client.py
yodu/helpers/__init__.py
yodu/helpers/action_helper.py
yodu/helpers/item_helper.py
yodu/models/__init__.py
yodu/models/action.py
yodu/models/category.py
yodu/models/item.py
yodu/models/request.py
yodu/provider/__init__.py
yodu/provider/helper.py
yodu/provider/provider_base.py
yodu/provider/providers/__init__.py
yodu/provider/providers/top_item_by_user_action/__init__.py
yodu/provider/providers/top_item_by_user_action/provider.py
yodu/provider/repo/__init__.py
yodu/recommeder/__init__.py
yodu/recommeder/recommender.py
yodu/recommeder/db/__init__.py
yodu/recommeder/db/influx_db.py
yodu/utils/__init__.py
yodu/utils/utils.py
yodu-0.0.4.dist-info/LICENSE
yodu-0.0.4.dist-info/METADATA
yodu-0.0.4.dist-info/WHEEL
yodu-0.0.4.dist-info/top_level.txt
yodu-0.0.4.dist-info/RECORD
