Metadata-Version: 2.1
Name: yodu
Version: 0.0.4
Summary: Generic Purpose Open Source Recommender System
Home-page: https://github.com/thegeeklabs/yodu.ai
Author: Shashank Agarwal
Author-email: shashank@thegeeklabs.com
License: Apache 2.0
Keywords: recommendations,recommendation,recommenders,recommender,system,engine,machine learning,python,AI,ML
Classifier: Development Status :: 1 - Planning
Classifier: Intended Audience :: Developers
Classifier: Intended Audience :: Information Technology
Classifier: Intended Audience :: Science/Research
Classifier: Topic :: Scientific/Engineering :: Artificial Intelligence
Classifier: Topic :: Software Development :: Libraries :: Python Modules
Classifier: Programming Language :: Python :: 3.6
Classifier: Programming Language :: Python :: 3.7
Classifier: Programming Language :: Python :: 3.8
Classifier: Programming Language :: Python :: 3.9
Classifier: Operating System :: Microsoft :: Windows
Classifier: Operating System :: POSIX :: Linux
Classifier: Operating System :: MacOS
Classifier: Topic :: Utilities
Classifier: License :: OSI Approved :: Apache Software License
Requires-Python: >=3.7
License-File: LICENSE
Requires-Dist: pydantic
Requires-Dist: typing
Requires-Dist: requests
Requires-Dist: elasticsearch
Requires-Dist: python-dotenv
Requires-Dist: ijson
